tordle/__init__.py
tordle/check.py
tordle/render.py
tordle/session.py
tordle/tordle.py
tordle/usa_english.txt
tordle/util.py
tordle/widgets.py
tordle/word_list.py
tordle-0.1.2.dist-info/entry_points.txt
tordle-0.1.2.dist-info/WHEEL
tordle-0.1.2.dist-info/METADATA
tordle-0.1.2.dist-info/RECORD
